[
  [
    { "code":  -11, "label": "shift", "type": "modifier" },
    { "code":    0, "type": "placeholder" },
    { "code":   -7, "label": "delete", "type": "enter_editing" }
  ],
  [
    { "code": -202, "label": "view_symbols", "type": "system_gui" },
    { "$": "auto_text_key", "code":  113, "label": "q", "groupId": 1 },
    { "code": -227, "label": "language_switch", "type": "system_gui" },
    { "code": -212, "label": "ime_ui_mode_media", "type": "system_gui" },
    { "code":   32, "label": "space" },
    { "$": "auto_text_key", "code":  122, "label": "z", "groupId": 2 },
    { "code":   10, "label": "enter", "groupId": 3, "type": "enter_editing" }
  ]
]
