{
  "all": {
    "ص": {
       "relevant": [
        { "code": 1590, "label": "ض" }
      ]
    },
    "half_space": {
       "relevant": [
        { "code": 1622, "label": "ٖ" },
        { "code": 1648, "label": "ٰ" },
        { "code": 1619, "label": "ٓ" },
        { "code": 1615, "label": "ُ" },
        { "code": 1616, "label": "ِ" },
        { "code": 1614, "label": "َ" },
        { "code": 1600, "label": "ـ" },
        { "code": 1621, "label": "ٕ" },
        { "code": 1618, "label": "ْ" },
        { "code": 1617, "label": "ّ" },
        { "code": 1612, "label": "ٌ" },
        { "code": 1613, "label": "ٍ" },
        { "code": 1620, "label": "ٔ" }
      ]
    },
    "ی": {
      "relevant": [
        { "code": 1574, "label": "ئ" },
        { "code": 1610, "label": "ي" },
        { "code": 1746, "label": "ے" }
      ]
    },
    "ا": {
      "main": { "code": 1570, "label": "آ"},
      "relevant": [
        { "code": 1649, "label": "ٱ" },
        { "code": 1569, "label": "ء" },
        { "code": 1571, "label": "أ" },
        { "code": 1573, "label": "إ" }
      ]
    },
    "ه": {
      "relevant": [
        { "code": 1729, "label": "ہ" },
        { "code": 1728, "label": "ۀ" },
        { "code": 1726, "label": "ھ" }
      ]
    },
    "ت": {
      "relevant": [
        { "code": 1579, "label": "ث" }
      ]
    },
    "ک": {
      "relevant": [
        { "code": 1706, "label": "ڪ"}
      ]
    },
    "ط": {
      "relevant": [
        { "code": 1592, "label": "ظ" }
      ]
    },
    "ز": {
      "relevant": [
        { "code": 1688, "label": "ژ" }
      ]
    },
    "و": {
      "relevant": [
        { "code": 1572, "label": "ؤ" }
      ]
    },
    "گ": {
      "relevant": [
        { "code": 1662, "label": "پ" }
      ]
    },
    "~right": {
      "main": { "code": 1567, "label": "؟"},
      "relevant": [
        { "code": 1563, "label": "؛" },
        { "code": 58, "label": ":"},
        { "code": 33, "label": "!" }
      ]
    }
  },
  "uri": {
    "~right": {
      "main": { "code": -255, "label": ".ir"},
      "relevant": [
        { "code": -255, "label": ".gov" },
        { "code": -255, "label": ".org" },
        { "code": -255, "label": ".edu" },
        { "code": -255, "label": ".com" },
        { "code": -255, "label": ".net" }
      ]
    }
  }
}
