[
  [
    { "code": 71905, "label": "ğ‘£¡", "type": "numeric", "popup": {
      "main": { "code":   49, "label": "1" },
      "relevant": [
        { "code": 8537, "label": "â…™" },
        { "code": 8528, "label": "â…" },
        { "code": 8539, "label": "â…›" },
        { "code": 8529, "label": "â…‘" },
        { "code": 8530, "label": "â…’" },
        { "code":  185, "label": "Â¹" },
        { "code":  189, "label": "Â½" },
        { "code": 8531, "label": "â…“" },
        { "code":  188, "label": "Â¼" },
        { "code": 8533, "label": "â…•" }
      ]
    } },
    { "code": 71906, "label": "ğ‘£¢", "type": "numeric", "popup": {
      "main": { "code":   50, "label": "2" },
      "relevant": [
        { "code": 8532, "label": "â…”" },
        { "code":  178, "label": "Â²" },
        { "code": 8534, "label": "â…–" }
      ]
    } },
    { "code": 71907, "label": "ğ‘££", "type": "numeric", "popup": {
      "main": { "code":   51, "label": "3" },
      "relevant": [
        { "code": 8535, "label": "â…—" },
        { "code":  190, "label": "Â¾" },
        { "code":  179, "label": "Â³" },
        { "code": 8540, "label": "â…œ" }
      ]
    } },
    { "code": 71908, "label": "ğ‘£¤", "type": "numeric", "popup": {
      "main": { "code":   52, "label": "4" },
      "relevant": [
        { "code": 8536, "label": "â…˜" },
        { "code": 8308, "label": "â´" }
      ]
    } },
    { "code": 71909, "label": "ğ‘£¥", "type": "numeric", "popup": {
      "main": { "code":   53, "label": "5" },
      "relevant": [
        { "code": 8538, "label": "â…š" },
        { "code": 8309, "label": "âµ" },
        { "code": 8541, "label": "â…" }
      ]
    } },
    { "code": 71910, "label": "ğ‘£¦", "type": "numeric", "popup": {
      "main": { "code":   54, "label": "6" },
      "relevant": [
        { "code": 8310, "label": "â¶" }
      ]
    } },
    { "code": 71911, "label": "ğ‘£§", "type": "numeric", "popup": {
      "main": { "code":   55, "label": "7" },
      "relevant": [
        { "code": 8542, "label": "â…" },
        { "code": 8311, "label": "â·" }
      ]
    } },
    { "code": 71912, "label": "ğ‘£¨", "type": "numeric", "popup": {
      "main": { "code":   56, "label": "8" },
      "relevant": [
        { "code": 8312, "label": "â¸" }
      ]
    } },
    { "code": 71913, "label": "ğ‘£©", "type": "numeric", "popup": {
      "main": { "code":   57, "label": "9" },
      "relevant": [
        { "code": 8313, "label": "â¹" }
      ]
    } },
    { "code": 71904, "label": "ğ‘£ ", "type": "numeric", "popup": {
      "main": { "code":   48, "label": "0" },
      "relevant": [
        { "code": 8319, "label": "â¿" },
        { "code": 8709, "label": "âˆ…" },
        { "code": 8304, "label": "â°" }
      ]
    } }
  ]
]
